kenarBot/__init__.py
kenarBot/app.py
kenarBot/consts.py
kenarBot/message_handler.py
kenarBot/types/__init__.py
kenarBot/types/actions.py
kenarBot/types/icons.py
kenarBot/types/inline_keyboard.py
kenarBot/types/messages.py
kenarbot-0.1.1.dist-info/licenses/LICENSE
kenarbot-0.1.1.dist-info/METADATA
kenarbot-0.1.1.dist-info/WHEEL
kenarbot-0.1.1.dist-info/top_level.txt
kenarbot-0.1.1.dist-info/RECORD
