Metadata-Version: 2.4
Name: kenarBot
Version: 0.1.1
Summary: KenarBot: A Python SDK for building Kenar messaging bots with an intuitive, teleBot-inspired syntax.
Home-page: https://github.com/Mobin-Pourabedini/KenarBot
Author: Mobin Pourabedini
Author-email: realmobinpourabedini@gmail.com
License: MIT
Keywords: bot,kenar,messaging,chat,api
Classifier: Programming Language :: Python :: 3
Classifier: License :: OSI Approved :: MIT License
Classifier: Operating System :: OS Independent
Requires-Python: >=3.6
License-File: LICENSE
Requires-Dist: Flask>=2.0.3
Requires-Dist: requests>=2.31.0
Requires-Dist: httpx>=0.25.0
Requires-Dist: loguru>=0.5.3
Dynamic: license-file
